src/__init__.py
src/config.py
src/models.py
src/cli/__init__.py
src/cli/commands.py
src/repositories/__init__.py
src/repositories/irepository.py
src/repositories/sql_repository.py
src/templates/__init__.py
repository_model_db-0.1.21.dist-info/LICENSE
repository_model_db-0.1.21.dist-info/METADATA
repository_model_db-0.1.21.dist-info/WHEEL
repository_model_db-0.1.21.dist-info/entry_points.txt
repository_model_db-0.1.21.dist-info/top_level.txt
repository_model_db-0.1.21.dist-info/RECORD
