Metadata-Version: 2.1
Name: repository-model-db
Version: 0.1.21
Summary: repository-model-db
Home-page: https://github.com/GustavoSwDaniel/repository-model-db
Author: GustavoSwDaniel
Author-email: <gustavodanieldetoledo@gmail.com.com>
License: MIT
Keywords: python
Platform: UNKNOWN
Classifier: Programming Language :: Python :: 3
Classifier: Operating System :: Unix
Classifier: Operating System :: MacOS :: MacOS X
Classifier: Operating System :: Microsoft :: Windows
License-File: LICENSE
Requires-Dist: SQLAlchemy
Requires-Dist: alembic
Requires-Dist: psycopg2-binary
Requires-Dist: wheel
Requires-Dist: Mako
Requires-Dist: click
